pyzoopla/__init__.py
pyzoopla/__main__.py
pyzoopla/base.py
pyzoopla/base_scraper.py
pyzoopla/for_sale.py
pyzoopla/listing.py
pyzoopla/prices.py
pyzoopla/properties.py
pyzoopla/scrape.py
pyzoopla/to_rent.py
pyzoopla/utils.py
pyzoopla-0.1.13.dist-info/METADATA
pyzoopla-0.1.13.dist-info/RECORD
pyzoopla-0.1.13.dist-info/WHEEL
pyzoopla-0.1.13.dist-info/top_level.txt
tests/__init__.py
tests/test_for_sale.py
tests/test_listing.py
tests/test_prices.py
tests/test_properties.py
tests/test_to_rent.py
tests/test_utils.py
tests/test_utils_data.py
