Metadata-Version: 2.1
Name: pyzoopla
Version: 0.1.13
Summary: A Python package to access information about properties from Zoopla
Home-page: https://github.com/imrankhan17/pyzoopla
Author: Imran Khan
Author-email: imrankhan17@hotmail.co.uk
License: MIT
Platform: UNKNOWN
Classifier: Programming Language :: Python :: 3
Classifier: License :: OSI Approved :: MIT License
Classifier: Operating System :: OS Independent
Requires-Dist: beautifulsoup4
Requires-Dist: bs4
Requires-Dist: lxml
Requires-Dist: numpy
Requires-Dist: pandas
Requires-Dist: PyMySQL
Requires-Dist: requests
